README.md
setup.py
rastercarve/__init__.py
rastercarve/__main__.py
rastercarve.egg-info/PKG-INFO
rastercarve.egg-info/SOURCES.txt
rastercarve.egg-info/dependency_links.txt
rastercarve.egg-info/entry_points.txt
rastercarve.egg-info/requires.txt
rastercarve.egg-info/top_level.txt