Metadata-Version: 2.1
Name: rastercarve
Version: 1.0.7
Summary: Generate G-code to engrave raster images
Home-page: https://github.com/built1n/rastercarve
Author: Franklin Wei
Author-email: franklin@rockbox.org
License: UNKNOWN
Platform: UNKNOWN
Classifier: Development Status :: 5 - Production/Stable
Classifier: Environment :: Console
Classifier: License :: OSI Approved :: GNU General Public License v2 or later (GPLv2+)
Classifier: Operating System :: OS Independent
Classifier: Programming Language :: Python :: 3
Classifier: Topic :: Scientific/Engineering :: Electronic Design Automation (EDA)
Classifier: Topic :: Utilities
Requires-Python: >=3.6
